tme_api/__init__.py
tme_api/cms/__init__.py
tme_api/cms/api.py
tme_api/cms/enums.py
tme_api/cms/exception.py
tme_api/cms/model.py
tme_api/cms/requests.py
tme_api/cms/responses.py
tme_api/cms/utils.py
tme_api-2023.11.17.dist-info/METADATA
tme_api-2023.11.17.dist-info/WHEEL
tme_api-2023.11.17.dist-info/top_level.txt
tme_api-2023.11.17.dist-info/RECORD
