Metadata-Version: 2.1
Name: tme-api
Version: 2023.11.17
Summary: tme_api
Home-page: https://github.com/ldsxp/tme_api
Author: lds
Author-email: 85176878@qq.com
License: GNU GPL 3
Download-URL: https://pypi.org/project/tme_api
Platform: any
Classifier: Development Status :: 5 - Production/Stable
Classifier: Intended Audience :: Developers
Classifier: License :: OSI Approved :: GNU General Public License (GPL)
Classifier: Operating System :: OS Independent
Classifier: Programming Language :: Python
Classifier: Programming Language :: Python :: 3.6
Requires-Dist: requests-toolbelt
Requires-Dist: requests
Requires-Dist: pydantic (<2,>=1.9.2)
Requires-Dist: spider-utils
